wagtail_herald/__init__.py
wagtail_herald/apps.py
wagtail_herald/telepath.py
wagtail_herald/urls.py
wagtail_herald/views.py
wagtail_herald/widgets.py
wagtail_herald/locale/en/LC_MESSAGES/django.mo
wagtail_herald/locale/en/LC_MESSAGES/django.po
wagtail_herald/locale/ja/LC_MESSAGES/django.mo
wagtail_herald/locale/ja/LC_MESSAGES/django.po
wagtail_herald/migrations/0001_initial.py
wagtail_herald/migrations/0002_seosettings_gtm_container_id.py
wagtail_herald/migrations/0003_seosettings_robots_txt_and_more.py
wagtail_herald/migrations/0004_remove_seosettings_bing_site_verification_and_more.py
wagtail_herald/migrations/0005_seosettings_custom_body_end_html.py
wagtail_herald/migrations/__init__.py
wagtail_herald/models/__init__.py
wagtail_herald/models/mixins.py
wagtail_herald/models/settings.py
wagtail_herald/static/wagtail_herald/css/schema-widget.css
wagtail_herald/static/wagtail_herald/js/schema-widget.iife.js
wagtail_herald/static/wagtail_herald/js/schema-widget.iife.js.map
wagtail_herald/static/wagtail_herald/js/schema-widget.js
wagtail_herald/static/wagtail_herald/js/schema-widget.js.map
wagtail_herald/templates/wagtail_herald/seo_body.html
wagtail_herald/templates/wagtail_herald/seo_head.html
wagtail_herald/templates/wagtail_herald/widgets/schema_widget.html
wagtail_herald/templatetags/__init__.py
wagtail_herald/templatetags/wagtail_herald.py
wagtail_herald-0.4.1.dist-info/METADATA
wagtail_herald-0.4.1.dist-info/WHEEL
wagtail_herald-0.4.1.dist-info/licenses/LICENSE
wagtail_herald-0.4.1.dist-info/RECORD
